onako/__init__.py
onako/cli.py
onako/server.py
onako/tmux_orchestrator.py
onako/static/index.html
onako/templates/com.onako.server.plist.tpl
onako/templates/onako.service.tpl
onako-0.3.0.dist-info/METADATA
onako-0.3.0.dist-info/WHEEL
onako-0.3.0.dist-info/entry_points.txt
onako-0.3.0.dist-info/top_level.txt
onako-0.3.0.dist-info/RECORD
