Metadata-Version: 2.4
Name: onako
Version: 0.3.0
Summary: Dispatch and monitor Claude Code tasks from your phone
Author: Amir
License-Expression: MIT
Project-URL: Repository, https://github.com/AzRu/onako
Keywords: claude,claude-code,tmux,orchestrator,ai
Requires-Python: >=3.10
Requires-Dist: fastapi>=0.100.0
Requires-Dist: uvicorn>=0.20.0
Requires-Dist: click>=8.0.0
Provides-Extra: dev
Requires-Dist: pytest>=7.0; extra == "dev"
Requires-Dist: httpx>=0.24.0; extra == "dev"
